{
  "version": 1,
  "sourceCredRefs": {
    "matthew-andrews/isomorphic-fetch": "2019-12-23T15:41:18.291Z",
    "chrisdickinson/raf": "2019-12-23T14:42:52.422Z",
    "then/promise": "2019-12-23T14:42:31.662Z",
    "sindresorhus/open": "2019-12-23T14:37:35.618Z",
    "sboudrias/inquirer.js": "2019-12-23T14:37:09.776Z",
    "gcanti/tcomb": "2019-12-23T14:34:20.734Z",
    "sass/node-sass": "2019-12-23T14:19:27.029Z",
    "standard-things/esm": "2019-12-23T13:42:26.394Z",
    "avoidwork/tiny-lru": "2019-12-23T12:25:45.604Z",
    "substack/json-stable-stringify": "2019-12-23T12:07:15.865Z",
    "lukechilds/keyv": "2019-12-23T11:34:12.238Z",
    "postcss/autoprefixer": "2019-12-23T10:45:32.763Z",
    "quasarframework/quasar-extras": "2019-12-23T10:25:17.778Z",
    "techfort/lokijs": "2019-12-23T10:12:13.758Z",
    "d3/d3-time": "2019-12-23T10:09:07.756Z",
    "tim-kos/node-retry": "2019-12-23T09:32:25.468Z",
    "liady/webpack-node-externals": "2019-12-23T09:28:20.090Z",
    "request/request": "2019-12-23T09:27:35.396Z",
    "markdalgleish/static-site-generator-webpack-plugin": "2019-12-23T09:18:07.950Z",
    "lukechilds/keyv-test-suite": "2019-12-23T08:32:46.068Z",
    "vuejs/eslint-plugin-vue": "2019-12-23T08:32:40.041Z",
    "avajs/ava": "2019-12-23T08:29:07.070Z",
    "d3/d3-format": "2019-12-23T08:12:26.797Z",
    "react-icons/react-icons": "2019-12-23T08:08:13.928Z",
    "rollup/babel-preset-es2015-rollup": "2019-12-23T08:07:17.234Z",
    "stiang/remove-markdown": "2019-12-23T08:06:50.134Z",
    "babel/babel-loader": "2019-12-23T07:45:36.998Z",
    "amio/badgen": "2019-12-23T07:41:25.801Z",
    "rollup/rollup-plugin-buble": "2019-12-23T07:17:04.593Z",
    "stylus/stylus": "2019-12-23T06:42:49.790Z",
    "fluture-js/fluture-retry": "2019-12-23T06:27:15.274Z",
    "multiformats/js-multihash": "2019-12-23T06:18:33.248Z",
    "substack/minimist": "2019-12-23T06:08:46.457Z",
    "nmfr/optimize-css-assets-webpack-plugin": "2019-12-23T06:08:29.054Z",
    "chalk/chalk": "2019-12-23T06:08:13.017Z",
    "isaacs/rimraf": "2019-12-23T05:36:10.557Z",
    "isaacs/minimatch": "2019-12-23T05:33:18.030Z",
    "sindresorhus/log-update": "2019-12-23T05:32:57.155Z",
    "chaijs/chai": "2019-12-23T05:22:31.577Z",
    "howardabrams/node-mocks-http": "2019-12-23T05:15:14.562Z",
    "fluture-js/fluture": "2019-12-23T05:14:36.246Z",
    "yannickcr/eslint-plugin-react": "2019-12-23T05:13:10.826Z",
    "chalk/strip-ansi": "2019-12-23T05:07:13.606Z",
    "chimurai/http-proxy-middleware": "2019-12-23T04:18:46.059Z",
    "googlechrome/workbox": "2019-12-23T03:44:48.770Z",
    "brianloveswords/base64url": "2019-12-23T03:36:50.232Z",
    "vkalinichev/postcss-rtl": "2019-12-23T03:36:41.810Z",
    "kangax/html-minifier": "2019-12-23T03:36:31.954Z",
    "mysticatea/eslint-plugin-node": "2019-12-23T03:22:21.504Z",
    "moxystudio/node-cross-spawn": "2019-12-23T03:21:08.869Z",
    "substack/node-mkdirp": "2019-12-23T03:10:30.706Z",
    "vuejs/vue-loader": "2019-12-23T02:41:37.911Z",
    "dustinjackson/html-webpack-inline-source-plugin": "2019-12-23T02:34:35.660Z",
    "geowarin/friendly-errors-webpack-plugin": "2019-12-23T02:29:38.093Z",
    "sindresorhus/user-home": "2019-12-23T02:29:19.654Z",
    "airbnb/babel-plugin-dynamic-import-node": "2019-12-23T02:06:56.912Z",
    "fluture-js/booture": "2019-12-23T01:18:10.569Z",
    "sgrondin/bottleneck": "2019-12-23T01:07:18.462Z",
    "expressjs/compression": "2019-12-23T00:51:27.855Z",
    "shama/stylus-loader": "2019-12-23T00:30:14.367Z",
    "sindresorhus/multimatch": "2019-12-23T00:29:34.803Z",
    "racker/node-elementtree": "2019-12-23T00:29:24.375Z",
    "segmentio/metalsmith": "2019-12-23T00:18:50.794Z",
    "substack/deep-freeze": "2019-12-22T23:39:31.557Z",
    "quorrajs/ouch": "2019-12-22T23:39:15.847Z",
    "tj/consolidate.js": "2019-12-22T23:29:02.882Z",
    "gajus/eslint-plugin-flowtype": "2019-12-22T23:28:07.509Z",
    "npm/node-semver": "2019-12-22T23:27:02.691Z",
    "gjtorikian/isbinaryfile": "2019-12-22T23:25:50.515Z",
    "fgnass/node-dev": "2019-12-22T23:25:27.212Z",
    "bevacqua/hash-sum": "2019-12-22T23:15:40.228Z",
    "adriantoine/enzyme-to-json": "2019-12-22T23:15:29.168Z",
    "chaijs/deep-eql": "2019-12-22T23:07:20.728Z",
    "survivejs/webpack-merge": "2019-12-22T23:07:09.407Z",
    "standard/eslint-config-standard": "2019-12-22T22:42:04.400Z",
    "d3/d3-time-format": "2019-12-22T22:31:18.510Z",
    "evcohen/eslint-plugin-jsx-a11y": "2019-12-22T22:20:45.833Z",
    "sindresorhus/globby": "2019-12-22T22:17:54.222Z",
    "nodeca/pako": "2019-12-22T22:07:53.398Z",
    "beanow/keyv-fs-sync": "2019-12-22T22:07:12.341Z",
    "davidchambers/xyz": "2019-12-22T21:41:07.181Z",
    "chalk/supports-color": "2019-12-22T21:40:56.313Z",
    "sindresorhus/ora": "2019-12-22T21:40:35.689Z",
    "danethurber/webpack-manifest-plugin": "2019-12-22T21:40:13.031Z",
    "sindresorhus/delay": "2019-12-22T21:20:11.213Z",
    "motdotla/dotenv": "2019-12-22T21:19:59.605Z",
    "eemeli/yaml": "2019-12-22T21:17:57.134Z",
    "benjamn/recast": "2019-12-22T21:17:35.630Z",
    "raszi/node-tmp": "2019-12-22T21:15:40.225Z",
    "auth0/node-jsonwebtoken": "2019-12-22T21:14:58.075Z",
    "rexxars/react-markdown": "2019-12-22T21:12:22.172Z",
    "d3/d3-array": "2019-12-22T21:08:51.539Z",
    "jgm/commonmark.js": "2019-12-22T21:08:32.481Z",
    "rollup/rollup-plugin-json": "2019-12-22T21:07:04.704Z",
    "jprichardson/node-fs-extra": "2019-12-22T20:44:45.406Z",
    "sindresorhus/tildify": "2019-12-22T20:41:32.463Z",
    "jantimon/html-webpack-plugin": "2019-12-22T20:28:34.297Z",
    "bripkens/connect-history-api-fallback": "2019-12-22T20:22:22.531Z",
    "jhamlet/svg-react-loader": "2019-12-22T20:08:36.496Z",
    "tleunen/babel-plugin-module-resolver": "2019-12-22T20:08:16.633Z",
    "sindresorhus/got": "2019-12-22T19:41:43.782Z",
    "d3/d3-scale-chromatic": "2019-12-22T19:37:04.368Z",
    "jfromaniello/selfsigned": "2019-12-22T19:29:02.343Z",
    "standard/eslint-plugin-standard": "2019-12-22T19:28:56.241Z",
    "typicode/husky": "2019-12-22T19:18:43.245Z",
    "istanbuljs/nyc": "2019-12-22T19:16:07.382Z",
    "postcss/postcss-safe-parser": "2019-12-22T19:11:18.385Z",
    "babel/babel-eslint": "2019-12-22T19:11:08.364Z",
    "flowtype/flow-bin": "2019-12-22T19:07:24.225Z",
    "fluture-js/fluture-hooks": "2019-12-22T19:06:51.747Z",
    "caolan/async": "2019-12-22T18:48:21.887Z",
    "neutrinojs/webpack-chain": "2019-12-22T18:41:25.607Z",
    "vuejs/preload-webpack-plugin": "2019-12-22T18:30:51.617Z",
    "d3/d3-scale": "2019-12-22T18:30:43.421Z",
    "lovell/sharp": "2019-12-22T18:30:11.923Z",
    "npm/validate-npm-package-name": "2019-12-22T18:21:10.529Z",
    "sindresorhus/object-assign": "2019-12-22T18:21:05.687Z",
    "isaacs/node-lru-cache": "2019-12-22T18:20:59.705Z",
    "mrmlnc/fast-glob": "2019-12-22T18:20:32.419Z",
    "khan/aphrodite": "2019-12-22T17:35:20.144Z",
    "sindresorhus/dot-prop": "2019-12-22T17:33:39.426Z",
    "bfncs/request-fluture": "2019-12-22T17:33:29.281Z",
    "iarna/iarna-toml": "2019-12-22T17:33:09.491Z",
    "joshuawise/better-sqlite3": "2019-12-22T17:22:37.737Z",
    "bradoyler/route-cache": "2019-12-22T17:14:19.978Z",
    "thgreasi/babel-plugin-system-import-transformer": "2019-12-22T17:14:13.556Z",
    "reacttraining/history": "2019-12-22T17:14:08.298Z",
    "moment/luxon": "2019-12-22T17:11:29.455Z",
    "webpack/webpack-dev-server": "2019-12-22T11:44:34.549Z",
    "webpack-contrib/terser-webpack-plugin": "2019-12-22T09:32:27.969Z",
    "webpack/memory-fs": "2019-12-22T07:19:33.450Z",
    "zeit/ms": "2019-12-22T06:36:48.821Z",
    "webpack-contrib/webpack-bundle-analyzer": "2019-12-22T06:36:06.531Z",
    "vuejs/vue-router": "2019-12-22T05:44:31.693Z",
    "vuejs/vue-style-loader": "2019-12-22T05:38:31.058Z",
    "webpack-contrib/url-loader": "2019-12-22T05:07:16.237Z",
    "yenshih/style-resources-loader": "2019-12-22T05:06:32.900Z",
    "webpack-contrib/file-loader": "2019-12-22T04:41:51.926Z",
    "webpack-contrib/mini-css-extract-plugin": "2019-12-22T04:27:42.169Z",
    "webpack/webpack-cli": "2019-12-22T04:12:51.242Z",
    "wycats/handlebars.js": "2019-12-22T03:42:54.621Z",
    "webpack-contrib/copy-webpack-plugin": "2019-12-22T03:35:37.165Z",
    "webpack/webpack-dev-middleware": "2019-12-22T03:33:34.082Z",
    "webpack-contrib/sass-loader": "2019-12-22T03:10:34.543Z",
    "watson/ci-info": "2019-12-22T02:06:32.543Z",
    "wearereasonablepeople/eslint-config-warp": "2019-12-22T01:16:18.684Z",
    "webpack-contrib/css-loader": "2019-12-21T22:14:12.399Z",
    "yyx990803/register-service-worker": "2019-12-21T21:35:17.363Z",
    "xjamundx/eslint-plugin-promise": "2019-12-21T21:35:08.677Z",
    "vuejs/vuex": "2019-12-21T21:34:32.270Z",
    "webpack-contrib/eslint-loader": "2019-12-21T21:17:31.742Z",
    "webpack-contrib/webpack-hot-middleware": "2019-12-21T20:07:49.317Z",
    "webpack-contrib/compression-webpack-plugin": "2019-12-21T19:42:12.417Z",
    "jefflau/jest-fetch-mock": "2019-12-21T19:21:07.535Z",
    "rollup/rollup": "2019-12-21T17:24:18.625Z",
    "axios/axios": "2019-12-21T11:27:35.916Z",
    "gre/json-beautify": "2019-12-21T06:08:15.245Z",
    "cssnano/cssnano": "2019-12-21T04:52:00.217Z",
    "mishoo/uglifyjs2": "2019-12-21T04:42:13.176Z",
    "quasarframework/quasar": "2019-12-21T02:25:40.462Z",
    "rollup/rollup-plugin-node-resolve": "2019-12-21T01:28:24.553Z",
    "rollup/rollup-plugin-commonjs": "2019-12-21T01:27:37.336Z",
    "recharts/recharts": "2019-12-21T00:45:24.005Z",
    "postcss/postcss-loader": "2019-12-20T16:14:57.636Z",
    "sinonjs/sinon": "2019-11-27T11:56:09.561Z",
    "paulmillr/chokidar": "2019-10-25T19:47:18.588Z"
  },
  "packageRefs": {
    "enzyme-to-json": "adriantoine/enzyme-to-json",
    "babel-plugin-dynamic-import-node": "airbnb/babel-plugin-dynamic-import-node",
    "enzyme": "airbnb/enzyme",
    "enzyme-adapter-react-16": "airbnb/enzyme",
    "badgen": "amio/badgen",
    "jsonwebtoken": "auth0/node-jsonwebtoken",
    "ava": "avajs/ava",
    "tiny-lru": "avoidwork/tiny-lru",
    "axios": "axios/axios",
    "@babel/core": "babel/babel",
    "@babel/plugin-proposal-class-properties": "babel/babel",
    "@babel/preset-env": "babel/babel",
    "@babel/preset-flow": "babel/babel",
    "@babel/preset-react": "babel/babel",
    "@babel/plugin-proposal-decorators": "babel/babel",
    "@babel/plugin-proposal-export-namespace-from": "babel/babel",
    "@babel/plugin-proposal-function-sent": "babel/babel",
    "@babel/plugin-proposal-json-strings": "babel/babel",
    "@babel/plugin-proposal-numeric-separator": "babel/babel",
    "@babel/plugin-proposal-throw-expressions": "babel/babel",
    "@babel/plugin-syntax-dynamic-import": "babel/babel",
    "@babel/plugin-syntax-import-meta": "babel/babel",
    "@babel/plugin-transform-runtime": "babel/babel",
    "@babel/runtime": "babel/babel",
    "@babel/runtime-corejs2": "babel/babel",
    "@babel/runtime-corejs3": "babel/babel",
    "babel-eslint": "babel/babel-eslint",
    "babel-loader": "babel/babel-loader",
    "keyv-fs-sync": "beanow/keyv-fs-sync",
    "recast": "benjamn/recast",
    "eslint-plugin-import": "benmosher/eslint-plugin-import",
    "hash-sum": "bevacqua/hash-sum",
    "request-fluture": "bfncs/request-fluture",
    "route-cache": "bradoyler/route-cache",
    "base64url": "brianloveswords/base64url",
    "connect-history-api-fallback": "bripkens/connect-history-api-fallback",
    "async": "caolan/async",
    "chai": "chaijs/chai",
    "deep-eql": "chaijs/deep-eql",
    "chalk": "chalk/chalk",
    "strip-ansi": "chalk/strip-ansi",
    "supports-color": "chalk/supports-color",
    "http-proxy-middleware": "chimurai/http-proxy-middleware",
    "raf": "chrisdickinson/raf",
    "cssnano": "cssnano/cssnano",
    "d3-array": "d3/d3-array",
    "d3-format": "d3/d3-format",
    "d3-scale": "d3/d3-scale",
    "d3-scale-chromatic": "d3/d3-scale-chromatic",
    "d3-time": "d3/d3-time",
    "d3-time-format": "d3/d3-time-format",
    "webpack-manifest-plugin": "danethurber/webpack-manifest-plugin",
    "xyz": "davidchambers/xyz",
    "html-webpack-inline-source-plugin": "dustinjackson/html-webpack-inline-source-plugin",
    "yaml": "eemeli/yaml",
    "eslint": "eslint/eslint",
    "eslint-plugin-jsx-a11y": "evcohen/eslint-plugin-jsx-a11y",
    "compression": "expressjs/compression",
    "express": "expressjs/express",
    "react-dev-utils": "facebook/create-react-app",
    "babel-jest": "facebook/jest",
    "jest": "facebook/jest",
    "react": "facebook/react",
    "react-dom": "facebook/react",
    "node-dev": "fgnass/node-dev",
    "flow-bin": "flowtype/flow-bin",
    "booture": "fluture-js/booture",
    "fluture": "fluture-js/fluture",
    "fluture-hooks": "fluture-js/fluture-hooks",
    "fluture-retry": "fluture-js/fluture-retry",
    "eslint-plugin-flowtype": "gajus/eslint-plugin-flowtype",
    "tcomb": "gcanti/tcomb",
    "friendly-errors-webpack-plugin": "geowarin/friendly-errors-webpack-plugin",
    "whatwg-fetch": "github/fetch",
    "download-git-repo": "gitlab:flippidippi/download-git-repo",
    "isbinaryfile": "gjtorikian/isbinaryfile",
    "workbox-webpack-plugin": "googlechrome/workbox",
    "json-beautify": "gre/json-beautify",
    "node-mocks-http": "howardabrams/node-mocks-http",
    "@iarna/toml": "iarna/iarna-toml",
    "minimatch": "isaacs/minimatch",
    "lru-cache": "isaacs/node-lru-cache",
    "rimraf": "isaacs/rimraf",
    "nyc": "istanbuljs/nyc",
    "html-webpack-plugin": "jantimon/html-webpack-plugin",
    "jest-fetch-mock": "jefflau/jest-fetch-mock",
    "selfsigned": "jfromaniello/selfsigned",
    "commonmark": "jgm/commonmark.js",
    "svg-react-loader": "jhamlet/svg-react-loader",
    "better-sqlite3": "joshuawise/better-sqlite3",
    "fs-extra": "jprichardson/node-fs-extra",
    "html-minifier": "kangax/html-minifier",
    "aphrodite": "khan/aphrodite",
    "webpack-node-externals": "liady/webpack-node-externals",
    "lodash.clonedeep": "lodash/lodash",
    "lodash.isequal": "lodash/lodash",
    "lodash.sortby": "lodash/lodash",
    "lodash.debounce": "lodash/lodash",
    "lodash.template": "lodash/lodash",
    "lodash.throttle": "lodash/lodash",
    "sharp": "lovell/sharp",
    "keyv": "lukechilds/keyv",
    "@keyv/test-suite": "lukechilds/keyv-test-suite",
    "static-site-generator-webpack-plugin": "markdalgleish/static-site-generator-webpack-plugin",
    "isomorphic-fetch": "matthew-andrews/isomorphic-fetch",
    "uglify-es": "mishoo/uglifyjs2",
    "mocha": "mochajs/mocha",
    "luxon": "moment/luxon",
    "dotenv": "motdotla/dotenv",
    "cross-spawn": "moxystudio/node-cross-spawn",
    "fast-glob": "mrmlnc/fast-glob",
    "multihashes": "multiformats/js-multihash",
    "eslint-plugin-node": "mysticatea/eslint-plugin-node",
    "webpack-chain": "neutrinojs/webpack-chain",
    "optimize-css-assets-webpack-plugin": "nmfr/optimize-css-assets-webpack-plugin",
    "pako": "nodeca/pako",
    "semver": "npm/node-semver",
    "validate-npm-package-name": "npm/validate-npm-package-name",
    "chokidar": "paulmillr/chokidar",
    "autoprefixer": "postcss/autoprefixer",
    "postcss-loader": "postcss/postcss-loader",
    "postcss-safe-parser": "postcss/postcss-safe-parser",
    "prettier": "prettier/prettier",
    "@quasar/fastclick": "quasarframework/fastclick",
    "@quasar/babel-preset-app": "quasarframework/quasar",
    "@quasar/extras": "quasarframework/quasar-extras",
    "ouch": "quorrajs/ouch",
    "elementtree": "racker/node-elementtree",
    "tmp": "raszi/node-tmp",
    "react-icons": "react-icons/react-icons",
    "history": "reacttraining/history",
    "react-router": "reacttraining/react-router",
    "recharts": "recharts/recharts",
    "request": "request/request",
    "react-markdown": "rexxars/react-markdown",
    "babel-preset-es2015-rollup": "rollup/babel-preset-es2015-rollup",
    "rollup": "rollup/rollup",
    "rollup-plugin-buble": "rollup/rollup-plugin-buble",
    "rollup-plugin-commonjs": "rollup/rollup-plugin-commonjs",
    "rollup-plugin-json": "rollup/rollup-plugin-json",
    "rollup-plugin-node-resolve": "rollup/rollup-plugin-node-resolve",
    "eslint-friendly-formatter": "royriojas/eslint-friendly-formatter",
    "node-sass": "sass/node-sass",
    "inquirer": "sboudrias/inquirer.js",
    "metalsmith": "segmentio/metalsmith",
    "bottleneck": "sgrondin/bottleneck",
    "stylus-loader": "shama/stylus-loader",
    "delay": "sindresorhus/delay",
    "dot-prop": "sindresorhus/dot-prop",
    "globby": "sindresorhus/globby",
    "got": "sindresorhus/got",
    "log-update": "sindresorhus/log-update",
    "multimatch": "sindresorhus/multimatch",
    "object-assign": "sindresorhus/object-assign",
    "open": "sindresorhus/open",
    "ora": "sindresorhus/ora",
    "tildify": "sindresorhus/tildify",
    "user-home": "sindresorhus/user-home",
    "sinon": "sinonjs/sinon",
    "esm": "standard-things/esm",
    "eslint-config-standard": "standard/eslint-config-standard",
    "eslint-plugin-standard": "standard/eslint-plugin-standard",
    "remove-markdown": "stiang/remove-markdown",
    "stylus": "stylus/stylus",
    "deep-freeze": "substack/deep-freeze",
    "json-stable-stringify": "substack/json-stable-stringify",
    "minimist": "substack/minimist",
    "mkdirp": "substack/node-mkdirp",
    "webpack-merge": "survivejs/webpack-merge",
    "lokijs": "techfort/lokijs",
    "promise": "then/promise",
    "babel-plugin-system-import-transformer": "thgreasi/babel-plugin-system-import-transformer",
    "retry": "tim-kos/node-retry",
    "consolidate": "tj/consolidate.js",
    "babel-plugin-module-resolver": "tleunen/babel-plugin-module-resolver",
    "husky": "typicode/husky",
    "postcss-rtl": "vkalinichev/postcss-rtl",
    "eslint-plugin-vue": "vuejs/eslint-plugin-vue",
    "@vue/preload-webpack-plugin": "vuejs/preload-webpack-plugin",
    "vue": "vuejs/vue",
    "vue-server-renderer": "vuejs/vue",
    "vue-template-compiler": "vuejs/vue",
    "vue-loader": "vuejs/vue-loader",
    "vue-router": "vuejs/vue-router",
    "vue-style-loader": "vuejs/vue-style-loader",
    "vuex": "vuejs/vuex",
    "ci-info": "watson/ci-info",
    "eslint-config-warp": "wearereasonablepeople/eslint-config-warp",
    "compression-webpack-plugin": "webpack-contrib/compression-webpack-plugin",
    "copy-webpack-plugin": "webpack-contrib/copy-webpack-plugin",
    "css-loader": "webpack-contrib/css-loader",
    "eslint-loader": "webpack-contrib/eslint-loader",
    "file-loader": "webpack-contrib/file-loader",
    "mini-css-extract-plugin": "webpack-contrib/mini-css-extract-plugin",
    "sass-loader": "webpack-contrib/sass-loader",
    "terser-webpack-plugin": "webpack-contrib/terser-webpack-plugin",
    "url-loader": "webpack-contrib/url-loader",
    "webpack-bundle-analyzer": "webpack-contrib/webpack-bundle-analyzer",
    "webpack-hot-middleware": "webpack-contrib/webpack-hot-middleware",
    "memory-fs": "webpack/memory-fs",
    "webpack": "webpack/webpack",
    "webpack-cli": "webpack/webpack-cli",
    "webpack-dev-middleware": "webpack/webpack-dev-middleware",
    "webpack-dev-server": "webpack/webpack-dev-server",
    "handlebars": "wycats/handlebars.js",
    "eslint-plugin-promise": "xjamundx/eslint-plugin-promise",
    "eslint-plugin-react": "yannickcr/eslint-plugin-react",
    "style-resources-loader": "yenshih/style-resources-loader",
    "register-service-worker": "yyx990803/register-service-worker",
    "ms": "zeit/ms"
  }
}